LICENSE
README.md
httpie_asap_auth.py
setup.cfg
setup.py
httpie_asap_auth.egg-info/PKG-INFO
httpie_asap_auth.egg-info/SOURCES.txt
httpie_asap_auth.egg-info/dependency_links.txt
httpie_asap_auth.egg-info/entry_points.txt
httpie_asap_auth.egg-info/not-zip-safe
httpie_asap_auth.egg-info/requires.txt
httpie_asap_auth.egg-info/top_level.txt