Metadata-Version: 2.1
Name: httpie-asap-auth
Version: 0.3.0
Summary: ASAP Auth plugin for HTTPie.
Home-page: https://github.com/jasonfriedland/httpie-asap-auth
Author: Jason Friedland
Author-email: jason@friedland.id.au
License: MIT
Download-URL: https://github.com/jasonfriedland/httpie-asap-auth
Platform: UNKNOWN
Classifier: Development Status :: 5 - Production/Stable
Classifier: Programming Language :: Python
Classifier: Programming Language :: Python :: 3
Classifier: Programming Language :: Python :: 3.7
Classifier: Programming Language :: Python :: 3.8
Classifier: Programming Language :: Python :: 3.9
Classifier: Environment :: Plugins
Classifier: License :: OSI Approved :: MIT License
Classifier: Topic :: Internet :: WWW/HTTP
Classifier: Topic :: Utilities
License-File: LICENSE
